italian_utils/__init__.py
italian_utils/models.py
italian_utils/utils.py
italian_utils/validators.py
italian_utils/management/__init__.py
italian_utils/management/commands/__init__.py
italian_utils/management/commands/importacomuni.py
italian_utils/migrations/0001_initial.py
italian_utils/migrations/0002_auto_20140828_1839.py
italian_utils/migrations/__init__.py
italian_utils/tests/__init__.py
italian_utils/tests/tests.py
django_italian_utils-0.3.3.dist-info/LICENSE
django_italian_utils-0.3.3.dist-info/METADATA
django_italian_utils-0.3.3.dist-info/WHEEL
django_italian_utils-0.3.3.dist-info/top_level.txt
django_italian_utils-0.3.3.dist-info/RECORD
