Metadata-Version: 2.1
Name: django-italian-utils
Version: 0.3.3
Summary: Libreria di utility per semplificare la creazione di applicazioni italiane.
Home-page: https://github.com/facciocose/django-italian-utils
Author: Luca Marra
Author-email: luca@facciocose.it
License: MIT License
Platform: UNKNOWN
Classifier: Environment :: Web Environment
Classifier: Framework :: Django
Classifier: Intended Audience :: Developers
Classifier: License :: OSI Approved :: MIT License
Classifier: Operating System :: OS Independent
Classifier: Programming Language :: Python
Classifier: Programming Language :: Python :: 3
Classifier: Programming Language :: Python :: 3.2
Classifier: Programming Language :: Python :: 3.3
Classifier: Topic :: Internet :: WWW/HTTP
Classifier: Topic :: Internet :: WWW/HTTP :: Dynamic Content
